{
  "black": {
    "$value": "{color.black}",
    "$type": "color",
    "themeable": true,
    "prefix": false
  },
  "white": {
    "$value": "{color.white}",
    "$type": "color",
    "themeable": true,
    "prefix": false
  },
  "blue": {
    "50": {
      "$value": "{color.blue.50}",
      "$type": "color",
      "themeable": true,
      "prefix": false
    },
    "100": {
      "$value": "{color.blue.100}",
      "$type": "color",
      "themeable": true,
      "prefix": false
    },
    "200": {
      "$value": "{color.blue.200}",
      "$type": "color",
      "themeable": true,
      "prefix": false
    },
    "300": {
      "$value": "{color.blue.300}",
      "$type": "color",
      "themeable": true,
      "prefix": false
    },
    "400": {
      "$value": "{color.blue.400}",
      "$type": "color",
      "themeable": true,
      "prefix": false
    },
    "500": {
      "$value": "{color.blue.500}",
      "$type": "color",
      "themeable": true,
      "prefix": false
    },
    "600": {
      "$value": "{color.blue.600}",
      "$type": "color",
      "themeable": true,
      "prefix": false
    },
    "700": {
      "$value": "{color.blue.700}",
      "$type": "color",
      "themeable": true,
      "prefix": false
    },
    "800": {
      "$value": "{color.blue.800}",
      "$type": "color",
      "themeable": true,
      "prefix": false
    },
    "900": {
      "$value": "{color.blue.900}",
      "$type": "color",
      "themeable": true,
      "prefix": false
    },
    "950": {
      "$value": "{color.blue.950}",
      "$type": "color",
      "themeable": true,
      "prefix": false
    }
  },
  "gray": {
    "10": {
      "$value": "{color.gray.10}",
      "$type": "color",
      "themeable": true,
      "prefix": false
    },
    "50": {
      "$value": "{color.gray.50}",
      "$type": "color",
      "themeable": true,
      "prefix": false
    },
    "100": {
      "$value": "{color.gray.100}",
      "$type": "color",
      "themeable": true,
      "prefix": false
    },
    "200": {
      "$value": "{color.gray.200}",
      "$type": "color",
      "themeable": true,
      "prefix": false
    },
    "300": {
      "$value": "{color.gray.300}",
      "$type": "color",
      "themeable": true,
      "prefix": false
    },
    "400": {
      "$value": "{color.gray.400}",
      "$type": "color",
      "themeable": true,
      "prefix": false
    },
    "500": {
      "$value": "{color.gray.500}",
      "$type": "color",
      "themeable": true,
      "prefix": false
    },
    "600": {
      "$value": "{color.gray.600}",
      "$type": "color",
      "themeable": true,
      "prefix": false
    },
    "700": {
      "$value": "{color.gray.700}",
      "$type": "color",
      "themeable": true,
      "prefix": false
    },
    "800": {
      "$value": "{color.gray.800}",
      "$type": "color",
      "themeable": true,
      "prefix": false
    },
    "900": {
      "$value": "{color.gray.900}",
      "$type": "color",
      "themeable": true,
      "prefix": false
    },
    "950": {
      "$value": "{color.gray.950}",
      "$type": "color",
      "themeable": true,
      "prefix": false
    }
  },
  "green": {
    "50": {
      "$value": "{color.green.50}",
      "$type": "color",
      "themeable": true,
      "prefix": false
    },
    "100": {
      "$value": "{color.green.100}",
      "$type": "color",
      "themeable": true,
      "prefix": false
    },
    "200": {
      "$value": "{color.green.200}",
      "$type": "color",
      "themeable": true,
      "prefix": false
    },
    "300": {
      "$value": "{color.green.300}",
      "$type": "color",
      "themeable": true,
      "prefix": false
    },
    "400": {
      "$value": "{color.green.400}",
      "$type": "color",
      "themeable": true,
      "prefix": false
    },
    "500": {
      "$value": "{color.green.500}",
      "$type": "color",
      "themeable": true,
      "prefix": false
    },
    "600": {
      "$value": "{color.green.600}",
      "$type": "color",
      "themeable": true,
      "prefix": false
    },
    "700": {
      "$value": "{color.green.700}",
      "$type": "color",
      "themeable": true,
      "prefix": false
    },
    "800": {
      "$value": "{color.green.800}",
      "$type": "color",
      "themeable": true,
      "prefix": false
    },
    "900": {
      "$value": "{color.green.900}",
      "$type": "color",
      "themeable": true,
      "prefix": false
    },
    "950": {
      "$value": "{color.green.950}",
      "$type": "color",
      "themeable": true,
      "prefix": false
    }
  },
  "orange": {
    "50": {
      "$value": "{color.orange.50}",
      "$type": "color",
      "themeable": true,
      "prefix": false
    },
    "100": {
      "$value": "{color.orange.100}",
      "$type": "color",
      "themeable": true,
      "prefix": false
    },
    "200": {
      "$value": "{color.orange.200}",
      "$type": "color",
      "themeable": true,
      "prefix": false
    },
    "300": {
      "$value": "{color.orange.300}",
      "$type": "color",
      "themeable": true,
      "prefix": false
    },
    "400": {
      "$value": "{color.orange.400}",
      "$type": "color",
      "themeable": true,
      "prefix": false
    },
    "500": {
      "$value": "{color.orange.500}",
      "$type": "color",
      "themeable": true,
      "prefix": false
    },
    "600": {
      "$value": "{color.orange.600}",
      "$type": "color",
      "themeable": true,
      "prefix": false
    },
    "700": {
      "$value": "{color.orange.700}",
      "$type": "color",
      "themeable": true,
      "prefix": false
    },
    "800": {
      "$value": "{color.orange.800}",
      "$type": "color",
      "themeable": true,
      "prefix": false
    },
    "900": {
      "$value": "{color.orange.900}",
      "$type": "color",
      "themeable": true,
      "prefix": false
    },
    "950": {
      "$value": "{color.orange.950}",
      "$type": "color",
      "themeable": true,
      "prefix": false
    }
  },
  "purple": {
    "50": {
      "$value": "{color.purple.50}",
      "$type": "color",
      "themeable": true,
      "prefix": false
    },
    "100": {
      "$value": "{color.purple.100}",
      "$type": "color",
      "themeable": true,
      "prefix": false
    },
    "200": {
      "$value": "{color.purple.200}",
      "$type": "color",
      "themeable": true,
      "prefix": false
    },
    "300": {
      "$value": "{color.purple.300}",
      "$type": "color",
      "themeable": true,
      "prefix": false
    },
    "400": {
      "$value": "{color.purple.400}",
      "$type": "color",
      "themeable": true,
      "prefix": false
    },
    "500": {
      "$value": "{color.purple.500}",
      "$type": "color",
      "themeable": true,
      "prefix": false
    },
    "600": {
      "$value": "{color.purple.600}",
      "$type": "color",
      "themeable": true,
      "prefix": false
    },
    "700": {
      "$value": "{color.purple.700}",
      "$type": "color",
      "themeable": true,
      "prefix": false
    },
    "800": {
      "$value": "{color.purple.800}",
      "$type": "color",
      "themeable": true,
      "prefix": false
    },
    "900": {
      "$value": "{color.purple.900}",
      "$type": "color",
      "themeable": true,
      "prefix": false
    },
    "950": {
      "$value": "{color.purple.950}",
      "$type": "color",
      "themeable": true,
      "prefix": false
    }
  },
  "red": {
    "50": {
      "$value": "{color.red.50}",
      "$type": "color",
      "themeable": true,
      "prefix": false
    },
    "100": {
      "$value": "{color.red.100}",
      "$type": "color",
      "themeable": true,
      "prefix": false
    },
    "200": {
      "$value": "{color.red.200}",
      "$type": "color",
      "themeable": true,
      "prefix": false
    },
    "300": {
      "$value": "{color.red.300}",
      "$type": "color",
      "themeable": true,
      "prefix": false
    },
    "400": {
      "$value": "{color.red.400}",
      "$type": "color",
      "themeable": true,
      "prefix": false
    },
    "500": {
      "$value": "{color.red.500}",
      "$type": "color",
      "themeable": true,
      "prefix": false
    },
    "600": {
      "$value": "{color.red.600}",
      "$type": "color",
      "themeable": true,
      "prefix": false
    },
    "700": {
      "$value": "{color.red.700}",
      "$type": "color",
      "themeable": true,
      "prefix": false
    },
    "800": {
      "$value": "{color.red.800}",
      "$type": "color",
      "themeable": true,
      "prefix": false
    },
    "900": {
      "$value": "{color.red.900}",
      "$type": "color",
      "themeable": true,
      "prefix": false
    },
    "950": {
      "$value": "{color.red.950}",
      "$type": "color",
      "themeable": true,
      "prefix": false
    }
  },
  "brand": {
    "charcoal": {
      "$value": "{color.brand.charcoal}",
      "$type": "color",
      "themeable": true,
      "prefix": false
    },
    "orange": {
      "01": {
        "$value": "{color.brand.orange.01}",
        "$type": "color",
        "themeable": true,
        "prefix": false
      },
      "02": {
        "$value": "{color.brand.orange.02}",
        "$type": "color",
        "themeable": true,
        "prefix": false
      },
      "03": {
        "$value": "{color.brand.orange.03}",
        "$type": "color",
        "themeable": true,
        "prefix": false
      }
    },
    "purple": {
      "01": {
        "$value": "{color.brand.purple.01}",
        "$type": "color",
        "themeable": true,
        "prefix": false
      },
      "02": {
        "$value": "{color.brand.purple.02}",
        "$type": "color",
        "themeable": true,
        "prefix": false
      }
    },
    "gray": {
      "01": {
        "$value": "{color.brand.gray.01}",
        "$type": "color",
        "themeable": true,
        "prefix": false
      },
      "02": {
        "$value": "{color.brand.gray.02}",
        "$type": "color",
        "themeable": true,
        "prefix": false
      },
      "03": {
        "$value": "{color.brand.gray.03}",
        "$type": "color",
        "themeable": true,
        "prefix": false
      },
      "04": {
        "$value": "{color.brand.gray.04}",
        "$type": "color",
        "themeable": true,
        "prefix": false
      },
      "05": {
        "$value": "{color.brand.gray.05}",
        "$type": "color",
        "themeable": true,
        "prefix": false
      }
    }
  }
}
